Metadata-Version: 2.1
Name: craft-text-detector-jsl
Version: 0.4.3
Summary: Fast and accurate text detection library built on CRAFT implementation
Home-page: https://github.com/fcakyon/craft_text_detector
Author: Fatih Cagatay Akyon
License: MIT
Keywords: machine-learning,deep-learning,ml,pytorch,text,text-detection,craft
Platform: UNKNOWN
Classifier: Development Status :: 5 - Production/Stable
Classifier: License :: OSI Approved :: MIT License
Classifier: Operating System :: OS Independent
Classifier: Intended Audience :: Developers
Classifier: Intended Audience :: Science/Research
Classifier: Programming Language :: Python :: 3
Classifier: Programming Language :: Python :: 3.6
Classifier: Programming Language :: Python :: 3.7
Classifier: Programming Language :: Python :: 3.8
Classifier: Topic :: Software Development :: Libraries
Classifier: Topic :: Software Development :: Libraries :: Python Modules
Classifier: Topic :: Education
Classifier: Topic :: Scientific/Engineering
Classifier: Topic :: Scientific/Engineering :: Artificial Intelligence
Classifier: Topic :: Scientific/Engineering :: Image Recognition
Requires-Python: >=3.7
Requires-Dist: gdown (>=3.10.1)
Requires-Dist: opencv-python (>=3.4.8.29,>=4.9.0.80)
Requires-Dist: scipy (>=1.3.2)
Requires-Dist: torch (>=1.6.0)
Requires-Dist: torchvision (>=0.7.0)
